forklet/__init__.py
forklet/__main__.py
forklet/config/settings.py
forklet/core/__init__.py
forklet/core/filter.py
forklet/core/orchestrator.py
forklet/core/__pycache__/__init__.cpython-310.pyc
forklet/core/__pycache__/filter.cpython-310.pyc
forklet/core/__pycache__/orchestrator.cpython-310.pyc
forklet/infrastructure/__init__.py
forklet/infrastructure/error_handler.py
forklet/infrastructure/logger.py
forklet/infrastructure/rate_limiter.py
forklet/infrastructure/retry_manager.py
forklet/infrastructure/__pycache__/__init__.cpython-310.pyc
forklet/infrastructure/__pycache__/error_handler.cpython-310.pyc
forklet/infrastructure/__pycache__/logger.cpython-310.pyc
forklet/infrastructure/__pycache__/rate_limiter.cpython-310.pyc
forklet/infrastructure/__pycache__/retry_manager.cpython-310.pyc
forklet/interfaces/api.py
forklet/interfaces/cli.py
forklet/interfaces/__pycache__/api.cpython-310.pyc
forklet/interfaces/__pycache__/cli.cpython-310.pyc
forklet/models/__init__.py
forklet/models/constants.py
forklet/models/__pycache__/__init__.cpython-310.pyc
forklet/models/__pycache__/constants.cpython-310.pyc
forklet/services/__init__.py
forklet/services/download.py
forklet/services/github_api.py
forklet/services/__pycache__/__init__.cpython-310.pyc
forklet/services/__pycache__/download.cpython-310.pyc
forklet/services/__pycache__/github_api.cpython-310.pyc
forklet-0.1.1.dist-info/licenses/LICENSE
forklet-0.1.1.dist-info/METADATA
forklet-0.1.1.dist-info/WHEEL
forklet-0.1.1.dist-info/entry_points.txt
forklet-0.1.1.dist-info/top_level.txt
forklet-0.1.1.dist-info/RECORD
