Metadata-Version: 2.4
Name: forklet
Version: 0.1.1
Summary: Download any file or folder from any GitHub repo by branch, tag, or commit with glob pattern filtering.
Author-email: AllDotPy <hello@alldotpy.com>
Maintainer-email: #Einswilli <einswilligoeh@email.com>
License:                                  Apache License
Project-URL: Repository, https://github.com/AllDotPy/Forklet
Project-URL: Tracker, https://github.com/AllDotPy/Forklet/issues
Keywords: forklet,CI/CD,github Downloader,github-files,pipelines,github clone
Requires-Python: >=3.10
License-File: LICENSE
Requires-Dist: aiofiles>=24.1.0
Requires-Dist: click>=8.2.1
Requires-Dist: httpx>=0.28.1
Requires-Dist: pydantic>=2.11.9
Requires-Dist: pygithub>=2.8.1
Requires-Dist: python-dotenv>=1.1.1
Requires-Dist: rich>=14.1.0
Requires-Dist: tqdm>=4.67.1
Provides-Extra: dev
Requires-Dist: black; extra == "dev"
Requires-Dist: mypy; extra == "dev"
Requires-Dist: twine; extra == "dev"
Requires-Dist: uv; extra == "dev"
Requires-Dist: build; extra == "dev"
Requires-Dist: pytest>=8.4.0; extra == "dev"
Requires-Dist: mkdocs>=1.6.1; extra == "dev"
Requires-Dist: setuptools>=80.8.0; extra == "dev"
Requires-Dist: mkdocs-material>=9.6.14; extra == "dev"
Requires-Dist: mkdocs-static-i18n>=1.3.0; extra == "dev"
Dynamic: license-file
